baekjoonapi-0.2.5.dist-info/METADATA
baekjoonapi-0.2.5.dist-info/WHEEL
baekjoonapi-0.2.5.dist-info/licenses/LICENSE.md
baekjoonapi/__init__.py
baekjoonapi-0.2.5.dist-info/RECORD
