Metadata-Version: 2.1
Name: baekjoonapi
Version: 0.2.5
Summary: baekjoonapi for python
Author-Email: MisileLaboratory <misileminecord@gmail.com>
License: MisileLab License
Requires-Python: <4,>=3.8
Requires-Dist: requests==2.31.0
Requires-Dist: bs4==0.0.2
Requires-Dist: lxml==5.2.1
Requires-Dist: random-user-agent==1.0.1
